Metadata-Version: 1.0
Name: rzl-dash-material-design
Version: 0.0.1
Summary: material design components for dash
Home-page: UNKNOWN
Author: rzachlamberty
Author-email: UNKNOWN
License: MIT
Platform: UNKNOWN
